django_integer_enum/__init__.py
django_integer_enum/enums.py
django_integer_enum/fields.py
django_integer_enum-0.1.0.dist-info/DESCRIPTION.rst
django_integer_enum-0.1.0.dist-info/METADATA
django_integer_enum-0.1.0.dist-info/RECORD
django_integer_enum-0.1.0.dist-info/WHEEL
django_integer_enum-0.1.0.dist-info/metadata.json
django_integer_enum-0.1.0.dist-info/top_level.txt
