Metadata-Version: 2.0
Name: django-integer-enum
Version: 0.1.0
Summary: Django model integer enum field
Home-page: https://github.com/localboy/django-integer-enum
Author: Mohammad Jakir Hossain
Author-email: mjakir.ddd@gmail.com
License: MIT license
Keywords: django_integer_enum
Platform: UNKNOWN
Classifier: Development Status :: 2 - Pre-Alpha
Classifier: Intended Audience :: Developers
Classifier: License :: OSI Approved :: MIT License
Classifier: Natural Language :: English
Classifier: Programming Language :: Python :: 2
Classifier: Programming Language :: Python :: 2.7
Classifier: Programming Language :: Python :: 3
Classifier: Programming Language :: Python :: 3.4
Classifier: Programming Language :: Python :: 3.5
Classifier: Programming Language :: Python :: 3.6
Classifier: Programming Language :: Python :: 3.7
